pyfindfiles/__init__.py
pyfindfiles/__main__.py
pyfindfiles/async_vid.py
pyfindfiles/project.py
pyfindfiles/text.py
pyfindfiles/video.py
pyfindfiles/tests/__init__.py
pyfindfiles/tests/test_project.py
pyfindfiles/tests/test_text.py
pyfindfiles/tests/test_video.py
pyfindfiles-1.6.0.dist-info/LICENSE.txt
pyfindfiles-1.6.0.dist-info/METADATA
pyfindfiles-1.6.0.dist-info/WHEEL
pyfindfiles-1.6.0.dist-info/top_level.txt
pyfindfiles-1.6.0.dist-info/RECORD
