Metadata-Version: 2.1
Name: pyfindfiles
Version: 1.6.0
Summary: Concurrent, pipelined text and binary file searching via pure Python, cross-platform.
Keywords: find,grep
Classifier: Development Status :: 5 - Production/Stable
Classifier: Environment :: Console
Classifier: Framework :: AsyncIO
Classifier: Intended Audience :: Developers
Classifier: Intended Audience :: End Users/Desktop
Classifier: License :: OSI Approved :: MIT License
Classifier: Operating System :: OS Independent
Classifier: Programming Language :: Python :: 3
Requires-Python: >=3.9
License-File: LICENSE.txt
Requires-Dist: python-dateutil
Provides-Extra: lint
Requires-Dist: flake8 ; extra == 'lint'
Requires-Dist: flake8-bugbear ; extra == 'lint'
Requires-Dist: flake8-builtins ; extra == 'lint'
Requires-Dist: flake8-blind-except ; extra == 'lint'
Requires-Dist: mypy ; extra == 'lint'
Requires-Dist: types-python-dateutil ; extra == 'lint'
Provides-Extra: tests
Requires-Dist: pytest ; extra == 'tests'
